redbot/__init__.py
redbot/cache_file.py
redbot/cli.py
redbot/daemon.py
redbot/speak.py
redbot/type.py
redbot/assets/prettify.js
redbot/assets/prettify.js.map
redbot/assets/red_style.css
redbot/assets/script.js
redbot/assets/script.js.map
redbot/assets/style.css
redbot/assets/icons/check-circle.svg
redbot/assets/icons/exclamation-circle.svg
redbot/assets/icons/info-circle.svg
redbot/assets/icons/question-circle.svg
redbot/assets/icons/times-circle.svg
redbot/assets/logo/apple-touch-icon-144x144.png
redbot/assets/logo/apple-touch-icon-152x152.png
redbot/assets/logo/favicon-16x16.png
redbot/assets/logo/favicon-32x32.png
redbot/assets/logo/favicon.ico
redbot/assets/logo/mstile-144x144.png
redbot/assets/logo/redbot-sq.png
redbot/formatter/__init__.py
redbot/formatter/har.py
redbot/formatter/html.py
redbot/formatter/html_base.py
redbot/formatter/slack.py
redbot/formatter/text.py
redbot/formatter/templates/footer.html
redbot/formatter/templates/response_finish.html
redbot/formatter/templates/response_multi_finish.html
redbot/formatter/templates/response_start.html
redbot/message/__init__.py
redbot/message/cache.py
redbot/message/link_parse.py
redbot/message/status.py
redbot/message/test_message.py
redbot/message/headers/__init__.py
redbot/message/headers/_notes.py
redbot/message/headers/_utils.py
redbot/message/headers/accept_ranges.py
redbot/message/headers/age.py
redbot/message/headers/allow.py
redbot/message/headers/cache_control.py
redbot/message/headers/connection.py
redbot/message/headers/connectiox.py
redbot/message/headers/content_base.py
redbot/message/headers/content_disposition.py
redbot/message/headers/content_encoding.py
redbot/message/headers/content_language.py
redbot/message/headers/content_length.py
redbot/message/headers/content_location.py
redbot/message/headers/content_md5.py
redbot/message/headers/content_range.py
redbot/message/headers/content_transfer_encoding.py
redbot/message/headers/content_type.py
redbot/message/headers/cteonnt_length.py
redbot-2023.9.5.dist-info/LICENSE.md
redbot-2023.9.5.dist-info/METADATA
redbot-2023.9.5.dist-info/WHEEL
redbot-2023.9.5.dist-info/entry_points.txt
redbot-2023.9.5.dist-info/top_level.txt
redbot-2023.9.5.dist-info/RECORD
