Metadata-Version: 2.1
Name: redbot
Version: 2023.9.5
Summary: REDbot is lint for HTTP.
Author-email: Mark Nottingham <mnot@mnot.net>
License: Copyright (c) 2008- Mark Nottingham
Project-URL: homepage, https://redbot.org/project/
Classifier: Operating System :: OS Independent
Classifier: Programming Language :: Python :: 3.9
Classifier: Development Status :: 4 - Beta
Classifier: Intended Audience :: Developers
Classifier: Intended Audience :: System Administrators
Classifier: Environment :: Web Environment
Classifier: Topic :: Internet :: WWW/HTTP
Classifier: Topic :: Software Development :: Testing
Classifier: Operating System :: Unix
Classifier: Operating System :: MacOS :: MacOS X
Classifier: License :: OSI Approved :: MIT License
Requires-Python: >=3.9
License-File: LICENSE.md
Requires-Dist: thor >=0.9.6
Requires-Dist: markdown >=2.6.5
Requires-Dist: netaddr >=0.7.19
Requires-Dist: Jinja2 >=2.11.1
Requires-Dist: typing-extensions >=4.3.0
Requires-Dist: MarkupSafe
Requires-Dist: importlib-resources
Provides-Extra: dev
Requires-Dist: mypy ; extra == 'dev'
Requires-Dist: playwright ; extra == 'dev'
Requires-Dist: black ; extra == 'dev'
Requires-Dist: pytest ; extra == 'dev'
Requires-Dist: pytest-md ; extra == 'dev'
Requires-Dist: validate-pyproject ; extra == 'dev'
Provides-Extra: systemd
Requires-Dist: cysystemd ; extra == 'systemd'
